{
  "vendor": "DEC",
  "family": "Alpha 21364",
  "codeName": "EV7",
  "model": null,
  "arch": {
    "name": "EV7",
    "isa": "Alpha",
    "isaVersion": null,
    "isaExtensions": [],
    "fpPipestages": 7,
    "intPipestages": 7,
    "maxUopIssuedPerCycle": 6,
    "ifu": 4,
    "lsfu": 2,
    "fpfu": 2,
    "tfu": 6,
    "maxInstDecoded": 4,
    "robSize": 80,
    "iwindow": 35,
    "ifQueue": 4,
    "bhtSize": 29696,
    "btbSize": 4096,
    "bpAcc": 0,
    "archIntReg": 39,
    "archFpReg": 31,
    "totalArchReg": null,
    "fpCoproc": null,
    "outOfOrder": true,
    "memoryBw": null,
    "integratedMc": null
  },
  "technology": {
    "name": "CMOS-8S3",
    "year": 1998,
    "technology": "CMOS",
    "featureSize": 0.18,
    "channelLength": 0.1,
    "metalLayers": 7,
    "metal": null,
    "vddNom": 1.5,
    "vth": null
  },
  "cache": {
    "L1": null,
    "L1I": null,
    "L1D": null,
    "L2": 1024,
    "L2Cores": 2,
    "L3": null,
    "L3Cores": null
  },
  "date": "2002-01-01",
  "clock": 1000,
  "maxClock": null,
  "mips": null,
  "threadsPerCore": 1,
  "cores": 1,
  "thermalPower": 125,
  "busWidth": 64,
  "transistors": 130,
  "dieSize": 397,
  "vdd": {
    "low": 1.5,
    "high": 1.5
  }
}