{
  "vendor": "Intel",
  "family": "Itanium 2",
  "codeName": "Montvale",
  "model": "9120N",
  "arch": {
    "name": "Montvale",
    "isa": "IA-64",
    "isaVersion": null,
    "isaExtensions": [],
    "fpPipestages": null,
    "intPipestages": null,
    "maxUopIssuedPerCycle": null,
    "ifu": null,
    "lsfu": null,
    "fpfu": null,
    "tfu": null,
    "maxInstDecoded": null,
    "robSize": null,
    "iwindow": null,
    "ifQueue": null,
    "bhtSize": null,
    "btbSize": null,
    "bpAcc": null,
    "archIntReg": null,
    "archFpReg": null,
    "totalArchReg": null,
    "fpCoproc": null,
    "outOfOrder": null,
    "memoryBw": null,
    "integratedMc": null
  },
  "technology": {
    "name": "P1262",
    "year": 2003,
    "technology": "CMOS",
    "featureSize": 0.09,
    "channelLength": 0.053,
    "metalLayers": 7,
    "metal": null,
    "vddNom": null,
    "vth": null
  },
  "cache": {
    "L1": null,
    "L1I": null,
    "L1D": null,
    "L2": 1024,
    "L2Cores": 2,
    "L3": null,
    "L3Cores": null
  },
  "date": "2007-10-01",
  "clock": 1400,
  "maxClock": null,
  "mips": null,
  "threadsPerCore": 2,
  "cores": 2,
  "thermalPower": 104,
  "busWidth": 64,
  "transistors": 1720,
  "dieSize": 596,
  "vdd": {
    "low": null,
    "high": null
  }
}